{
  "users": [
    {
      "id": "1",
      "usuario": "John Doe",
      "email": "john.due@gmail.com"
    }
  ],
  "heroes": [
    {
      "id": "0ae9d761-a446-4c73-bf47-375812b5d969",
      "superhero": "Batman",
      "publisher": "DC Comics",
      "alter_ego": "Bruce Wayne",
      "first_appearance": "Detective Comics #27",
      "characters": "Bruce Wayne"
    },
    {
      "id": "8cb24c19-ec3e-4049-aa1b-366216df130b",
      "superhero": "Superman",
      "publisher": "DC Comics",
      "alter_ego": "Kal-El",
      "first_appearance": "Action Comics #1",
      "characters": "Kal-El"
    },
    {
      "id": "f07289a5-e5bc-4146-b0c7-b8cf9963ec32",
      "superhero": "Flash",
      "publisher": "DC Comics",
      "alter_ego": "Jay Garrick",
      "first_appearance": "Flash Comics #1",
      "characters": "Jay Garrick, Barry Allen, Wally West, Bart Allen"
    },
    {
      "id": "9c2ad3ee-5620-4a3c-9fd5-863fab0f9378",
      "superhero": "Green Lantern",
      "publisher": "DC Comics",
      "alter_ego": "Alan Scott",
      "first_appearance": "All-American Comics #16",
      "characters": "Alan Scott, Hal Jordan, Guy Gardner, John Stewart, Kyle Raynor, Jade, Sinestro, Simon Baz"
    },
    {
      "id": "3c6dbe7f-0800-4a4c-bb73-518b4c6e208c",
      "superhero": "Green Arrow",
      "publisher": "DC Comics",
      "alter_ego": "Oliver Queen",
      "first_appearance": "More Fun Comics #73",
      "characters": "Oliver Queen"
    },
    {
      "id": "933b699e-093e-4905-914d-6609b71d61f8",
      "superhero": "Wonder Woman",
      "publisher": "DC Comics",
      "alter_ego": "Princess Diana",
      "first_appearance": "All Star Comics #8",
      "characters": "Princess Diana"
    },
    {
      "id": "ded4ac15-b6f9-4faa-9447-7d3f8e600853",
      "superhero": "Martian Manhunter",
      "publisher": "DC Comics",
      "alter_ego": "J\"onn J\"onzz",
      "first_appearance": "Detective Comics #225",
      "characters": "Martian Manhunter"
    },
    {
      "id": "8b0a8d77-bc39-4873-92d5-2812518b7e21",
      "superhero": "Robin/Nightwing",
      "publisher": "DC Comics",
      "alter_ego": "Dick Grayson",
      "first_appearance": "Detective Comics #38",
      "characters": "Dick Grayson"
    },
    {
      "id": "4012828b-4884-4d70-8ab2-2c078b37cb8c",
      "superhero": "Blue Beetle",
      "publisher": "DC Comics",
      "alter_ego": "Dan Garret",
      "first_appearance": "Mystery Men Comics #1",
      "characters": "Dan Garret, Ted Kord, Jaime Reyes"
    },
    {
      "id": "5b488c33-241f-4047-acca-a4f9adadfa88",
      "superhero": "Black Canary",
      "publisher": "DC Comics",
      "alter_ego": "Dinah Drake",
      "first_appearance": "Flash Comics #86",
      "characters": "Dinah Drake, Dinah Lance"
    },
    {
      "id": "69612bec-7cc1-40e3-97c9-82621bc7ded0",
      "superhero": "Spider Man",
      "publisher": "Marvel Comics",
      "alter_ego": "Peter Parker",
      "first_appearance": "Amazing Fantasy #15",
      "characters": "Peter Parker"
    },
    {
      "id": "39a15d43-5822-427a-8cfd-8acba87cbc65",
      "superhero": "Captain America",
      "publisher": "Marvel Comics",
      "alter_ego": "Steve Rogers",
      "first_appearance": "Captain America Comics #1",
      "characters": "Steve Rogers"
    },
    {
      "id": "b7b8e2ac-3e2d-43d5-a212-54eebab301d5",
      "superhero": "Iron Man",
      "publisher": "Marvel Comics",
      "alter_ego": "Tony Stark",
      "first_appearance": "Tales of Suspense #39",
      "characters": "Tony Stark"
    },
    {
      "id": "684d027d-1d88-4331-93d0-199866fae299",
      "superhero": "Thor",
      "publisher": "Marvel Comics",
      "alter_ego": "Thor Odinson",
      "first_appearance": "Journey into Myster #83",
      "characters": "Thor Odinson"
    },
    {
      "id": "23f6c957-02d3-499d-8a52-9ae0e2bed1f8",
      "superhero": "Hulk",
      "publisher": "Marvel Comics",
      "alter_ego": "Bruce Banner",
      "first_appearance": "The Incredible Hulk #1",
      "characters": "Bruce Banner"
    },
    {
      "id": "12b3ab73-f8c3-4577-8351-5f36234a2a40",
      "superhero": "Wolverine",
      "publisher": "Marvel Comics",
      "alter_ego": "James Howlett",
      "first_appearance": "The Incredible Hulk #180",
      "characters": "James Howlett"
    },
    {
      "id": "5e724c38-97ad-46ee-a454-e2ee5693426b",
      "superhero": "Daredevil",
      "publisher": "Marvel Comics",
      "alter_ego": "Matthew Michael Murdock",
      "first_appearance": "Daredevil #1",
      "characters": "Matthew Michael Murdock"
    },
    {
      "id": "b7532e1c-42a9-4916-8080-e3833fad0928",
      "superhero": "Hawkeye",
      "publisher": "Marvel Comics",
      "alter_ego": "Clinton Francis Barton",
      "first_appearance": "Tales of Suspense #57",
      "characters": "Clinton Francis Barton"
    },
    {
      "id": "52ab74f9-bfe5-421e-9cd4-9396a5ad1cdc",
      "superhero": "Cyclops",
      "publisher": "Marvel Comics",
      "alter_ego": "Scott Summers",
      "first_appearance": "X-Men #1",
      "characters": "Scott Summers"
    },
    {
      "id": "4978b16b-fc11-4edd-be94-98deff28b303",
      "superhero": "Silver Surfer",
      "publisher": "Marvel Comics",
      "alter_ego": "Norrin Radd",
      "first_appearance": "The Fantastic Four #48",
      "characters": "Norrin Radd"
    }
  ]
}
